vibescraper/__init__.py
vibescraper/brave_search.py
vibescraper/change_search_api.py
vibescraper/check_api_keys.py
vibescraper/config.py
vibescraper/db_schema.py
vibescraper/google_search.py
vibescraper/html_parser.py
vibescraper/json_utils.py
vibescraper/main.py
vibescraper/openai_utils.py
vibescraper/page_embedder.py
vibescraper/timer_decorator.py
vibescraper/vibe_search.py
vibescraper-0.1.6.dist-info/LICENSE
vibescraper-0.1.6.dist-info/METADATA
vibescraper-0.1.6.dist-info/WHEEL
vibescraper-0.1.6.dist-info/entry_points.txt
vibescraper-0.1.6.dist-info/RECORD
