Metadata-Version: 2.3
Name: vibescraper
Version: 0.1.6
Summary: A semantic web scraping and summarization toolkit.
Author: u2084511felix
Author-email: 79988595+u2084511felix@users.noreply.github.com
Requires-Python: >=3.13,<4.0
Classifier: Programming Language :: Python :: 3
Classifier: Programming Language :: Python :: 3.13
Requires-Dist: beautifulsoup4 (>=4.13.4,<5.0.0)
Requires-Dist: google-api-python-client (>=2.168.0,<3.0.0)
Requires-Dist: html5lib (>=1.1,<2.0)
Requires-Dist: numpy (>=2.2.5,<3.0.0)
Requires-Dist: openai (>=1.76.2,<2.0.0)
Requires-Dist: pandas (>=2.2.3,<3.0.0)
Requires-Dist: requests (>=2.32.3,<3.0.0)
Requires-Dist: sqlalchemy (>=2.0.40,<3.0.0)
Requires-Dist: tiktoken (>=0.9.0,<0.10.0)
